splitter_mr/__init__.py
splitter_mr/embedding/__init__.py
splitter_mr/embedding/base_embedding.py
splitter_mr/embedding/embeddings/__init__.py
splitter_mr/embedding/embeddings/anthropic_embedding.py
splitter_mr/embedding/embeddings/azure_openai_embedding.py
splitter_mr/embedding/embeddings/gemini_embedding.py
splitter_mr/embedding/embeddings/huggingface_embedding.py
splitter_mr/embedding/embeddings/openai_embedding.py
splitter_mr/model/__init__.py
splitter_mr/model/base_model.py
splitter_mr/model/models/__init__.py
splitter_mr/model/models/anthropic_model.py
splitter_mr/model/models/azure_openai_model.py
splitter_mr/model/models/gemini_model.py
splitter_mr/model/models/grok_model.py
splitter_mr/model/models/huggingface_model.py
splitter_mr/model/models/openai_model.py
splitter_mr/reader/__init__.py
splitter_mr/reader/base_reader.py
splitter_mr/reader/readers/__init__.py
splitter_mr/reader/readers/docling_reader.py
splitter_mr/reader/readers/markitdown_reader.py
splitter_mr/reader/readers/vanilla_reader.py
splitter_mr/reader/utils/__init__.py
splitter_mr/reader/utils/docling_utils.py
splitter_mr/reader/utils/html_to_markdown.py
splitter_mr/reader/utils/pdfplumber_reader.py
splitter_mr/schema/__init__.py
splitter_mr/schema/constants.py
splitter_mr/schema/exceptions.py
splitter_mr/schema/models.py
splitter_mr/schema/prompts.py
splitter_mr/schema/warnings.py
splitter_mr/splitter/__init__.py
splitter_mr/splitter/base_splitter.py
splitter_mr/splitter/splitters/__init__.py
splitter_mr/splitter/splitters/character_splitter.py
splitter_mr/splitter/splitters/code_splitter.py
splitter_mr/splitter/splitters/header_splitter.py
splitter_mr/splitter/splitters/html_tag_splitter.py
splitter_mr/splitter/splitters/json_splitter.py
splitter_mr/splitter/splitters/keyword_splitter.py
splitter_mr/splitter/splitters/paged_splitter.py
splitter_mr/splitter/splitters/paragraph_splitter.py
splitter_mr/splitter/splitters/recursive_splitter.py
splitter_mr-1.1.0.dist-info/licenses/LICENSE
splitter_mr-1.1.0.dist-info/METADATA
splitter_mr-1.1.0.dist-info/WHEEL
splitter_mr-1.1.0.dist-info/top_level.txt
splitter_mr-1.1.0.dist-info/RECORD
