Metadata-Version: 2.4
Name: splitter-mr
Version: 1.1.0
Summary: A modular text splitting library.
Author-email: Andrés Herencia <andresherencia2000@gmail.com>
License: MIT License
Project-URL: homepage, https://github.com/andreshere00/splitter_mr
Project-URL: repository, https://github.com/andreshere00/splitter_mr
Requires-Python: >=3.11
License-File: LICENSE
Requires-Dist: beautifulsoup4>=4.13.4
Requires-Dist: fastparquet>=2024.11.0
Requires-Dist: ffmpeg>=1.4
Requires-Dist: ffmpeg-downloader>=0.4.0
Requires-Dist: gitpython>=3.1.45
Requires-Dist: langchain-text-splitters>=0.3.8
Requires-Dist: nltk>=3.9.1
Requires-Dist: numpy>=2.3.0
Requires-Dist: openpyxl>=3.1.5
Requires-Dist: pdfplumber>=0.11.7
Requires-Dist: pymupdf>=1.26.1
Requires-Dist: pypdf>=5.9.0
Requires-Dist: pyyaml>=6.0.2
Requires-Dist: reportlab>=4.4.3
Requires-Dist: spacy>=3.8.7
Requires-Dist: svglib>=1.5.1
Requires-Dist: tiktoken>=0.9.0
Requires-Dist: xlrd>=2.0.1
Provides-Extra: markitdown
Requires-Dist: markitdown[all]==0.1.2; extra == "markitdown"
Requires-Dist: azure-ai-documentintelligence>=1.0.2; extra == "markitdown"
Requires-Dist: azure-core>=1.34.0; extra == "markitdown"
Requires-Dist: azure-identity>=1.23.0; extra == "markitdown"
Provides-Extra: docling
Requires-Dist: docling>=2.36.0; extra == "docling"
Provides-Extra: multimodal
Requires-Dist: easyocr>=1.7.2; extra == "multimodal"
Requires-Dist: torch<3.0,>=2.7.1; extra == "multimodal"
Requires-Dist: torchvision<0.23,>=0.22.1; extra == "multimodal"
Requires-Dist: opencv-python-headless>=4.11.0.86; extra == "multimodal"
Requires-Dist: onnxruntime>=1.22.0; extra == "multimodal"
Requires-Dist: pillow>=11.2.1; extra == "multimodal"
Requires-Dist: scikit-image>=0.25.2; extra == "multimodal"
Requires-Dist: imageio>=2.37.0; extra == "multimodal"
Requires-Dist: shapely>=2.1.1; extra == "multimodal"
Requires-Dist: google-genai>=1.32.0; extra == "multimodal"
Requires-Dist: transformers>=4.52.4; extra == "multimodal"
Requires-Dist: tokenizers>=0.21.1; extra == "multimodal"
Requires-Dist: speechrecognition>=3.14.3; extra == "multimodal"
Requires-Dist: pydub>=0.25.1; extra == "multimodal"
Requires-Dist: openai>=1.99.9; extra == "multimodal"
Requires-Dist: gitpython>=3.1.45; extra == "multimodal"
Requires-Dist: sentence-transformers>=5.1.0; extra == "multimodal"
Requires-Dist: torch>=2.7.1; extra == "multimodal"
Requires-Dist: voyageai>=0.3.4; extra == "multimodal"
Requires-Dist: pip>=25.2; extra == "multimodal"
Requires-Dist: xai-sdk>=1.0.1; extra == "multimodal"
Provides-Extra: all
Requires-Dist: markitdown[all]==0.1.2; extra == "all"
Requires-Dist: docling>=2.36.0; extra == "all"
Requires-Dist: easyocr>=1.7.2; extra == "all"
Requires-Dist: torch<3.0,>=2.7.1; extra == "all"
Requires-Dist: torchvision<0.23,>=0.22.1; extra == "all"
Requires-Dist: opencv-python-headless>=4.11.0.86; extra == "all"
Requires-Dist: onnxruntime>=1.22.0; extra == "all"
Requires-Dist: pillow>=11.2.1; extra == "all"
Requires-Dist: scikit-image>=0.25.2; extra == "all"
Requires-Dist: imageio>=2.37.0; extra == "all"
Requires-Dist: shapely>=2.1.1; extra == "all"
Requires-Dist: transformers>=4.52.4; extra == "all"
Requires-Dist: tokenizers>=0.21.1; extra == "all"
Requires-Dist: speechrecognition>=3.14.3; extra == "all"
Requires-Dist: google-genai>=1.32.0; extra == "all"
Requires-Dist: pydub>=0.25.1; extra == "all"
Requires-Dist: azure-ai-documentintelligence>=1.0.2; extra == "all"
Requires-Dist: azure-core>=1.34.0; extra == "all"
Requires-Dist: azure-identity>=1.23.0; extra == "all"
Requires-Dist: xai-sdk>=1.0.1; extra == "all"
Requires-Dist: openai>=1.99.9; extra == "all"
Requires-Dist: gitpython>=3.1.45; extra == "all"
Requires-Dist: sentence-transformers>=5.1.0; extra == "all"
Requires-Dist: torch>=2.7.1; extra == "all"
Requires-Dist: voyageai>=0.3.4; extra == "all"
Dynamic: license-file
